[
  {
    "file": "raw/staging_diarrhea_by_state_wide/Encounters_Crosstab_2026-07-16T10_25_36.xlsx",
    "md5": "7cd4992f0b95c791124a57ef1c0c186d",
    "date_processed": "2026-07-16 11:33:36.160356",
    "Session Title": "Number of Encounters by State of Residence and Diagnosis (All)",
    "Session ID": "2842865",
    "Data Model": "Encounters",
    "Population Base": "All Encounters",
    "Population Criteria Filters": "Country of Residence: United States of America",
    "Session Date Range": "6/23/2023 - 6/22/2026 (Based On Encounter Start Date)",
    "Measure": "Number of Encounters",
    "Export User": "Anne Shapiro",
    "Date of Export": "7/16/2026"
  }
]
